CHANGELOG.md
LICENSE
MANIFEST.in
README.md
setup.cfg
setup.py
pip_services3_messaging/__init__.py
pip_services3_messaging.egg-info/PKG-INFO
pip_services3_messaging.egg-info/SOURCES.txt
pip_services3_messaging.egg-info/dependency_links.txt
pip_services3_messaging.egg-info/requires.txt
pip_services3_messaging.egg-info/top_level.txt
pip_services3_messaging.egg-info/zip-safe
pip_services3_messaging/build/DefaultMessagingFactory.py
pip_services3_messaging/build/IMessageQueueFactory.py
pip_services3_messaging/build/MemoryMessageQueueFactory.py
pip_services3_messaging/build/MessageQueueFactory.py
pip_services3_messaging/build/__init__.py
pip_services3_messaging/connect/IMessageQueueConnection.py
pip_services3_messaging/connect/__init__.py
pip_services3_messaging/queues/CachedMessageQueue.py
pip_services3_messaging/queues/CallbackMessageReceiver.py
pip_services3_messaging/queues/IMessageQueue.py
pip_services3_messaging/queues/IMessageReceiver.py
pip_services3_messaging/queues/LockedMessage.py
pip_services3_messaging/queues/MemoryMessageQueue.py
pip_services3_messaging/queues/MessageEnvelope.py
pip_services3_messaging/queues/MessageQueue.py
pip_services3_messaging/queues/MessagingCapabilities.py
pip_services3_messaging/queues/__init__.py
pip_services3_messaging/test/TestMessageReceiver.py
pip_services3_messaging/test/__init__.py
test/build/__init__.py
test/build/test_MemoryMessageQueueFactory.py
test/queues/MessageQueueFixture.py
test/queues/__init__.py
test/queues/test_MemoryMessageQueue.py
test/queues/test_MessageEnvelop.py